spglib/__init__.py
spglib/_spglib.cpython-39-darwin.so
spglib/_version.py
spglib/include/spglib.h
spglib/lib/libsymspg.2.4.0.dylib
spglib/lib/libsymspg.2.dylib
spglib/lib/libsymspg.dylib
spglib/spglib.py
spglib-2.4.0.dist-info/METADATA
spglib-2.4.0.dist-info/WHEEL
spglib-2.4.0.dist-info/entry_points.txt
spglib-2.4.0.dist-info/licenses/COPYING
spglib-2.4.0.dist-info/RECORD
