Metadata-Version: 2.1
Name: spglib
Version: 2.4.0
Summary: This is the spglib module.
Home-page: https://spglib.readthedocs.io/
Author-Email: Atsushi Togo <atz.togo@gmail.com>
Maintainer-Email: Atsushi Togo <atz.togo@gmail.com>, Cristian Le <git@lecris.dev>, Kohei Shinohara <kshinohara0508@gmail.com>
License: BSD-3-Clause
Classifier: Topic :: Scientific/Engineering :: Physics
Classifier: Intended Audience :: Science/Research
Classifier: Programming Language :: C
Classifier: Operating System :: Unix
Classifier: Operating System :: MacOS
Classifier: Operating System :: Microsoft :: Windows
Classifier: License :: OSI Approved :: BSD License
Classifier: Programming Language :: C
Classifier: Programming Language :: Python :: 3
Classifier: Programming Language :: Python :: 3 :: Only
Classifier: Programming Language :: Python :: 3.8
Classifier: Programming Language :: Python :: 3.9
Classifier: Programming Language :: Python :: 3.10
Classifier: Programming Language :: Python :: 3.11
Classifier: Programming Language :: Python :: 3.12
Classifier: Development Status :: 5 - Production/Stable
Project-URL: Homepage, https://spglib.readthedocs.io/
Project-URL: Documentation, https://spglib.readthedocs.io/
Project-URL: Repository, https://github.com/spglib/spglib
Project-URL: Changelog, https://spglib.readthedocs.io/en/latest/releases.html
Requires-Python: >=3.8
Requires-Dist: numpy>=1.20
Requires-Dist: typing-extensions; python_version < "3.9"
Requires-Dist: importlib-resources; python_version < "3.10"
Requires-Dist: pytest; extra == "test"
Requires-Dist: pyyaml; extra == "test"
Requires-Dist: Sphinx>=7.0; extra == "docs"
Requires-Dist: sphinxcontrib-bibtex>=2.5; extra == "docs"
Requires-Dist: sphinx-book-theme; extra == "docs"
Requires-Dist: sphinx-autodoc2; extra == "docs"
Requires-Dist: myst-parser>=2.0; extra == "docs"
Requires-Dist: linkify-it-py; extra == "docs"
Requires-Dist: spglib[test]; extra == "test-cov"
Requires-Dist: pytest-cov; extra == "test-cov"
Requires-Dist: spglib[test]; extra == "test-benchmark"
Requires-Dist: pytest-benchmark; extra == "test-benchmark"
Requires-Dist: spglib[test]; extra == "dev"
Requires-Dist: pre-commit; extra == "dev"
Requires-Dist: spglib[docs]; extra == "doc"
Requires-Dist: spglib[test]; extra == "testing"
Provides-Extra: test
Provides-Extra: docs
Provides-Extra: test-cov
Provides-Extra: test-benchmark
Provides-Extra: dev
Provides-Extra: doc
Provides-Extra: testing
